{
  "title": "Your journey to perfection",
  "subtitle": "Refined stitch by stitch—from first consultation to final fit, every step is crafted with care",
  "steps": [
    {
      "icon": "images/icons/conversation.svg",
      "icon_alt": "Consultation",
      "heading": "Consultation",
      "text": "Meet with your Master Tailor to discuss your style, preferences, and occasion."
    },
    {
      "icon": "images/icons/fabric-selection.svg",
      "icon_alt": "Fabric selection",
      "heading": "Fabric Selection",
      "text": "Choose from our exclusive collection of the finest fabrics for your handcrafted piece."
    },
    {
      "icon": "images/icons/measurements.svg",
      "icon_alt": "Measurements",
      "heading": "Measurements",
      "text": "Measured by hand to ensure a flawless fit—every detail matters for a suit designed for your body."
    },
    {
      "icon": "images/icons/fitting.svg",
      "icon_alt": "Fitting",
      "heading": "Fitting",
      "text": "Try on your suit—your fit—and we make any adjustments so every detail is right."
    },
    {
      "icon": "images/icons/delivery.svg",
      "icon_alt": "Delivery",
      "heading": "Final Delivery",
      "text": "Receive your masterpiece, perfectly crafted and ready to make an impression. We ship worldwide."
    }
  ],
  "cta_text": "Ready to find your fit?",
  "cta_label": "Contact us",
  "cta_href": "#contact"
}
